{
  "neoforge:conditions": [
    {
      "type": "neoforge:mod_loaded",
      "modid": "advanced_ae"
    }
  ],
  "type": "advanced_ae:react",
  "input_energy": 500000,
  "input_fluid": {
    "amount": 500,
    "ingredient": "minecraft:water"
  },
  "input_items": [
    {
      "amount": 32,
      "ingredient": "#c:dusts/ender_pearl"
    },
    {
      "amount": 32,
      "ingredient": "minecraft:iron_ingot"
    },
    {
      "amount": 32,
      "ingredient": "ae2:certus_quartz_dust"
    }
  ],
  "itemOutput": {
    "count": 64,
    "id": "ae2omnicells:ender_ingot"
  }
}