{
  "parent": "minecraft:recipes/root",
  "criteria": {
    "has_correct_unit": {
      "conditions": {
        "items": [
          {
            "items": "ae2omnicells:complex_crafting_unit_block"
          }
        ]
      },
      "trigger": "minecraft:inventory_changed"
    },
    "has_the_recipe": {
      "conditions": {
        "recipe": "ae2omnicells:crafting_unit/shapelesscomplex_crafting_storage_1k_block"
      },
      "trigger": "minecraft:recipe_unlocked"
    }
  },
  "requirements": [
    [
      "has_the_recipe",
      "has_correct_unit"
    ]
  ],
  "rewards": {
    "recipes": [
      "ae2omnicells:crafting_unit/shapelesscomplex_crafting_storage_1k_block"
    ]
  }
}